{
  "type": "horseman",
  "expRequiredForLevelUp": 100,
  "expGainWhenKilled": 40,
  "hitpoints": 60.0,
  "damage": 20.0,
  "attackTimerMax": 2.0,
  "movementSpeed": 60.0,
  "colliderRadius": 7.0,
  "cost": 80,
  "unlockCost": 50,
  "ai": {
    "type": 0,
    "range": -1.0
  },
  "animations": [
    {
      "jsonfilename": "assets/units/horseman.json"
    }
  ],
  "upgrades": [
    {
      "name": "carrot of agility",
      "iconPath": "assets/images/upgrades/carrot_of_agility.png",
      "upgCost": 200,
      "movementSpeed": {
        "add": 10.0,
        "factor": 0.0
      },
      "attackTimerMax": {
        "add": 0.0,
        "factor": -0.2
      }
    }
  ]
}
